eigengen/__init__.py
eigengen/chat.py
eigengen/eigengen.py
eigengen/gitfiles.py
eigengen/indexing.py
eigengen/keybindings.py
eigengen/log.py
eigengen/meld.py
eigengen/operations.py
eigengen/progress.py
eigengen/prompts.py
eigengen/providers.py
eigengen/utils.py
eigengen-0.2.0.dist-info/LICENSE
eigengen-0.2.0.dist-info/METADATA
eigengen-0.2.0.dist-info/WHEEL
eigengen-0.2.0.dist-info/entry_points.txt
eigengen-0.2.0.dist-info/top_level.txt
eigengen-0.2.0.dist-info/RECORD
