Metadata-Version: 2.1
Name: eigengen
Version: 0.2.0
Summary: EigenGen is a CLI LLM frontend for code generation with support for claude, gpt4 and llama3.1:70b.
Home-page: https://github.com/lleukkun/eigengen
Author: Lauri Leukkunen
Author-email: lauri.leukkunen@gmail.com
License: MIT
Classifier: Programming Language :: Python :: 3
Classifier: License :: OSI Approved :: MIT License
Classifier: Operating System :: OS Independent
Requires-Python: >=3.6
License-File: LICENSE
Requires-Dist: annotated-types ==0.7.0
Requires-Dist: anthropic ==0.34.2
Requires-Dist: anyio ==4.6.0
Requires-Dist: certifi ==2024.8.30
Requires-Dist: charset-normalizer ==3.3.2
Requires-Dist: colorama ==0.4.6
Requires-Dist: distro ==1.9.0
Requires-Dist: fastapi ==0.115.0
Requires-Dist: filelock ==3.16.1
Requires-Dist: fsspec ==2024.9.0
Requires-Dist: google-ai-generativelanguage ==0.6.10
Requires-Dist: google-api-core ==2.20.0
Requires-Dist: google-api-python-client ==2.144.0
Requires-Dist: google-auth ==2.35.0
Requires-Dist: google-auth-httplib2 ==0.2.0
Requires-Dist: google-generativeai ==0.8.2
Requires-Dist: googleapis-common-protos ==1.65.0
Requires-Dist: groq ==0.11.0
Requires-Dist: h11 ==0.14.0
Requires-Dist: httpcore ==1.0.6
Requires-Dist: httpx ==0.27.2
Requires-Dist: huggingface-hub ==0.25.1
Requires-Dist: idna ==3.10
Requires-Dist: jiter ==0.5.0
Requires-Dist: mistralai ==1.1.0
Requires-Dist: msgpack ==1.1.0
Requires-Dist: openai ==1.51.0
Requires-Dist: packaging ==24.1
Requires-Dist: pydantic ==2.9.2
Requires-Dist: pydantic-core ==2.23.4
Requires-Dist: Pygments ==2.18.0
Requires-Dist: pyperclip ==1.9.0
Requires-Dist: prompt-toolkit ==3.0.48
Requires-Dist: PyYAML ==6.0.2
Requires-Dist: requests ==2.32.3
Requires-Dist: setuptools ==75.1.0
Requires-Dist: sniffio ==1.3.1
Requires-Dist: tokenizers ==0.20.0
Requires-Dist: tqdm ==4.66.5
Requires-Dist: typing-extensions ==4.12.2
Requires-Dist: urllib3 ==2.2.3
Requires-Dist: uvicorn ==0.31.0
